polidoro_argument/__init__.py
polidoro_argument/argument.py
polidoro_argument/argument_parser.py
polidoro_argument/command.py
polidoro_argument/custom_action.py
polidoro_py_argument-2.1.0.dist-info/LICENSE
polidoro_py_argument-2.1.0.dist-info/METADATA
polidoro_py_argument-2.1.0.dist-info/WHEEL
polidoro_py_argument-2.1.0.dist-info/top_level.txt
polidoro_py_argument-2.1.0.dist-info/RECORD
