Metadata-Version: 2.1
Name: polidoro-py-argument
Version: 2.1.0
Summary: Package to create command line arguments for Python.
Home-page: https://github.com/heitorpolidoro/py-argument
Author: Heitor Polidoro
License: unlicense
Platform: UNKNOWN
Classifier: Programming Language :: Python :: 3
Classifier: License :: OSI Approved :: MIT License
Classifier: Operating System :: OS Independent
